wapl/__init__.py
wapl/wapl.py
wavepl-0.0.5.dist-info/METADATA
wavepl-0.0.5.dist-info/WHEEL
wavepl-0.0.5.dist-info/top_level.txt
wavepl-0.0.5.dist-info/RECORD
