Metadata-Version: 2.1
Name: wavepl
Version: 0.0.5
Summary: Library for processing WAV files.
Home-page: https://github.com/Krishna-Sivakumar/wapl
Author: Krishna Sivakumar
Author-email: krishnasivaprogrammer@gmail.com
License: UNKNOWN
Platform: UNKNOWN
Requires-Dist: numpy
